nestipy_db/__init__.py
nestipy_db/db_builder.py
nestipy_db/db_cli.py
nestipy_db/db_command.py
nestipy_db/db_decorator.py
nestipy_db/db_meta.py
nestipy_db/db_middleware.py
nestipy_db/db_model.py
nestipy_db/db_module.py
nestipy_db/db_service.py
nestipy_db/db_util.py
nestipy_db/static/favicon.ico
nestipy_db/static/placeholder.svg
nestipy_db/static/robots.txt
nestipy_db/static/test.txt
nestipy_db/static/assets/index-BY5ffRRz.js
nestipy_db/static/assets/index-yLpKmjW5.css
nestipy_db/stubs/model.stub
nestipy_db/utils/__init__.py
nestipy_db/utils/transformer.py
nestipy_db/views/index.html
nestipy_db-0.1.2.dist-info/METADATA
nestipy_db-0.1.2.dist-info/WHEEL
nestipy_db-0.1.2.dist-info/entry_points.txt
nestipy_db-0.1.2.dist-info/licenses/LICENSE
nestipy_db-0.1.2.dist-info/RECORD
