Metadata-Version: 2.4
Name: nestipy-db
Version: 0.1.2
Summary: Nestipy dababase adapter for edgy
Author-email: Tsiresy Milà <tsiresymila@gmail.com>
License-File: LICENSE
Requires-Python: >=3.11
Requires-Dist: autoflake>=2.3.1
Requires-Dist: autopep8>=2.3.2
Requires-Dist: click-aliases>=1.0.5
Requires-Dist: edgy>=0.33.0
Requires-Dist: inflect>=7.5.0
Requires-Dist: isort>=5.13.2
Requires-Dist: pyjwt>=2.10.1
Requires-Dist: python-multipart>=0.0.9
